BCN/BCNClassifier.py
BCN/BCNRegressor.py
BCN/__init__.py
BCN-0.7.1.dist-info/LICENSE
BCN-0.7.1.dist-info/METADATA
BCN-0.7.1.dist-info/WHEEL
BCN-0.7.1.dist-info/top_level.txt
BCN-0.7.1.dist-info/RECORD
