Metadata-Version: 2.1
Name: BCN
Version: 0.7.1
Summary: Boosted Configuration Networks
Home-page: https://github.com/Techtonique/bcn_python
Author: T. Moudiki
Author-email: thierry.moudiki@gmail.com
License: BSD license
Keywords: BCN,Machine Learning,Statistical Learning
Platform: UNKNOWN
Classifier: Development Status :: 2 - Pre-Alpha
Classifier: Intended Audience :: Developers
Classifier: License :: OSI Approved :: BSD License
Classifier: Natural Language :: English
Classifier: Programming Language :: Python :: 3
Classifier: Programming Language :: Python :: 3.6
Classifier: Programming Language :: Python :: 3.7
Classifier: Programming Language :: Python :: 3.8
Requires-Python: >=3.6
License-File: LICENSE
Requires-Dist: joblib
Requires-Dist: numpy
Requires-Dist: rpy2
Requires-Dist: scikit-learn
